{
  "$schema": "https://schema.tauri.app/config/2/capability",
  "identifier": "default",
  "description": "Standard-Berechtigungen für Klartext",
  "windows": ["main"],
  "permissions": [
    "core:default",
    "core:window:allow-start-dragging",
    "core:window:allow-toggle-maximize",
    "core:window:allow-set-fullscreen",
    "core:window:allow-close",
    "shell:allow-open",
    "dialog:allow-open",
    "dialog:allow-save",
    "fs:allow-read-file",
    "fs:allow-write-file",
    {
      "identifier": "fs:allow-write-text-file",
      "allow": [
        { "path": "$HOME/**" },
        { "path": "$DESKTOP/**" },
        { "path": "$DOCUMENT/**" },
        { "path": "$DOWNLOAD/**" }
      ]
    },
    {
      "identifier": "fs:allow-read-text-file",
      "allow": [
        { "path": "$HOME/**" },
        { "path": "$DESKTOP/**" },
        { "path": "$DOCUMENT/**" },
        { "path": "$DOWNLOAD/**" }
      ]
    },
    "allow-read-dropped-file"
  ]
}
